perfectem/__init__.py
perfectem/common.py
perfectem/config.py
perfectem/utils.py
perfectem/scripts/__init__.py
perfectem/scripts/afis.py
perfectem/scripts/eucentricity.py
perfectem/scripts/gain_reference.py
perfectem/scripts/gold_diffraction.py
perfectem/scripts/info_limit.py
perfectem/scripts/mag_anisotropy.py
perfectem/scripts/point_resolution.py
perfectem/scripts/spatial_coherence.py
perfectem/scripts/stage_drift.py
perfectem/scripts/thon_rings.py
perfectem/scripts/tilt_axis.py
perfectem-0.9.2.dist-info/LICENSE
perfectem-0.9.2.dist-info/METADATA
perfectem-0.9.2.dist-info/WHEEL
perfectem-0.9.2.dist-info/entry_points.txt
perfectem-0.9.2.dist-info/top_level.txt
perfectem-0.9.2.dist-info/RECORD
