Metadata-Version: 2.1
Name: perfectem
Version: 0.9.2
Summary: Run TEM performance tests with SerialEM
Home-page: https://github.com/azazellochg/perfectem
Author: Grigory Sharov
Author-email: gsharov@mrc-lmb.cam.ac.uk
Project-URL: Bug Reports, https://github.com/azazellochg/perfectem/issues
Project-URL: Source, https://github.com/azazellochg/perfectem
Keywords: cryo-em python serialem
Classifier: Development Status :: 3 - Alpha
Classifier: License :: OSI Approved :: GNU General Public License v3 (GPLv3)
Classifier: Programming Language :: Python :: 3
Requires-Python: >=3.6
License-File: LICENSE
Requires-Dist: mrcfile
Requires-Dist: numpy
Requires-Dist: scipy
Requires-Dist: matplotlib
Provides-Extra: dev
Requires-Dist: mypy ; extra == 'dev'
